flagger/__init__.py
flagger/exceptions.py
flagger/flagger.py
tests/__init__.py
tests/test_flagger.py
simple_flagger_private-0.1.dist-info/LICENSE
simple_flagger_private-0.1.dist-info/METADATA
simple_flagger_private-0.1.dist-info/WHEEL
simple_flagger_private-0.1.dist-info/top_level.txt
simple_flagger_private-0.1.dist-info/RECORD
