Metadata-Version: 2.1
Name: simple-flagger-private
Version: 0.1
Summary: A simple package for a flag parsing
Home-page: https://github.com/Doneeel/simple-flagger
Author: Doneeel
Author-email: doneeel08@gmail.com
Classifier: Programming Language :: Python :: 3
Classifier: License :: OSI Approved :: MIT License
Classifier: Operating System :: OS Independent
Requires-Python: >=3.10
License-File: LICENSE
